Workbook

Sheet PL Statement
C3: 2019 | D3: =C3+1 -> 2020 | E3: =D3+1 -> 2021 | F3: =E3+1 -> 2022 | G3: =F3+1 -> 2023
A4: 1 | B4: Income
A5: a | B5: Revenue from operations | C5: 73571.9 | D5: 83443.6 | E5: 88650.1 | F5: 106341.9 | G5: 115992.6
A6: b | B6: Other income | C6: 877 | D6: 1042.2 | E6: 2332.1 | F6: 1626.5 | G6: 2160.8
B7: Total income | C7: 74448.9 | D7: 84485.8 | E7: 90982.2 | F7: 107968.4 | G7: 118153.4
A8: 2 | B8: Expenses
A9: a | B9: Cost of materials consumed | C9: 18111.4 | D9: 21318.3 | E9: 23945.4 | F9: 32260.6 | G9: 30569.2
A10: b | B10: Purchases of stock-in-trade | C10: 11301.9 | D10: 14430.6 | E10: 14377.6 | F10: 14897.1 | G10: 13875.5
A11: c | B11: Changes in inventories of finished goods, work-in-progress and stock-in-trade | C11: 36.4 | D11: -2299.5 | E11: -3338.4 | F11: -5354.8 | G11: 4623.7
A12: d | B12: Employee benefits expense | C12: 13624.6 | D12: 15054.9 | E12: 16210.3 | F12: 19627.1 | G12: 21313.5
A13: e | B13: Finance costs | C13: 546.3 | D13: 650.6 | E13: 589.2 | F13: 523.7 | G13: 1073.6
A14: f | B14: Depreciation and amortisation expense | C14: 1931.8 | D14: 2527.6 | E14: 2745.8 | F14: 3039.6 | G14: 3104.2
A15: g | B15: Other expenses | C15: 19349.9 | D15: 20205.4 | E15: 18031.3 | F15: 24382.7 | G15: 29516.2
B16: Total expenses | C16: 64902.3 | D16: =SUM(D9:D15) -> 71887.9 | E16: 72561.2 | F16: 89376 | G16: 104075.9
A17: 3 | B17: Profit before exceptional items and tax (1) - (2) | C17: =C7-C16 -> 9546.6 | D17: =D7-D16 -> 12597.9 | E17: 18421 | F17: 18592.4 | G17: 14077.5
A18: 4 | B18: Exceptional items | C18: 0 | D18: 0 | E18: 0 | F18: -149.6 | G18: -1029.8
A19: 5 | B19: Profit before tax (3) + (4) | C19: =C17+C18 -> 9546.6 | D19: =SUM(D17:D18) -> 12597.9 | E19: 18421 | F19: 18442.8 | G19: 13047.7
A20: 6 | B20: Tax expense
A21: a | B21: Current tax | C21: 2291.7 | D21: 3542.5 | E21: 3965.3 | F21: 3619.8 | G21: 2739
A22: b | B22: Deferred tax charge/(credit) (net) | C22: -481.5 | D22: -2123.9 | E22: -1722 | F22: -1980.2 | G22: 240.6
B23: Total tax expenses (a + b) | C23: 1810.2 | D23: 1418.6 | E23: 2243.3 | F23: 1639.6 | G23: 2979.6
A24: c | B24: Tax adjustment of earlier periods | C24: 0 | D24: -313.8 | E24: 0 | F24: 0 | G24: 0
B25: Total tax expenses (a + b + c) | C25: 1810.2 | D25: =SUM(D23:D24) -> 1104.8 | E25: =SUM(E23:E24) -> 2243.3 | F25: =SUM(F23:F24) -> 1639.6 | G25: =SUM(G23:G24) -> 2979.6
A26: 7 | B26: Profit for the year (5) - (6) | C26: 7736.4 | D26: 11493.1 | E26: 16177.7 | F26: 16803.2 | G26: 10068.1
A27: 8 | B27: Profit attributable to Non-Controlling Interest | C27: 131.3 | D27: 222.4 | E27: 327.5 | F27: 347 | G27: 226.4
A28: 9 | B28: Profit attributable to Owners of the Company (7) - (8) | C28: 7605.1 | D28: =D26-D27 -> 11270.7 | E28: 15850.2 | F28: 16456.2 | G28: 9841.7
A29: 10 | B29: Other comprehensive income
A30: a | B30: (i) Items that will not be reclassified subsequently to profit or loss | C30: -69.4 | D30: -280.9 | E30: -89.2 | F30: -90.9 | G30: -48.7
B31: (ii) Income tax relating to items that will not be reclassified to profit or loss | C31: 23.7 | D31: 96.5 | E31: 29.9 | F31: 33.2 | G31: 16.1
A32: b | B32: (i) Items that will be reclassified to profit or loss | C32: 355.7 | D32: 453 | E32: -283.7 | F32: 399.1 | G32: 1181.6
B33: (ii) Income tax relating to items that will be reclassified to profit or loss | C33: 0 | D33: 0 | E33: 0 | F33: 0 | G33: 0
B34: Total of Other Comprehensive Income/(Loss) for the year, net of tax | C34: 310 | D34: 268.6 | E34: -343 | F34: 341.4 | G34: 1149
A35: 11 | B35: Other Comprehensive Income/(Loss) attributable to Non-Controlling Interest | C35: -1.1 | D35: -5.4 | E35: -3.4 | F35: -4.1 | G35: -4.1
A36: 12 | B36: Other Comprehensive Income/(Loss) attributable to Owners of the Company (10) - (11) | C36: 311.1 | D36: 274 | E36: -339.6 | F36: 345.5 | G36: 1153.1
A37: 13 | B37: Total Comprehensive Income for the year (7) + (10) | C37: 8046.4 | D37: 11761.7 | E37: 15834.7 | F37: 17144.6 | G37: 11217.1
A38: 14 | B38: Total Comprehensive Income/(Loss) attributable to Non-Controlling Interest (8) + (11) | C38: 130.2 | D38: 217 | E38: 324.1 | F38: 342.9 | G38: 222.3
A39: 15 | B39: Total Comprehensive Income/(Loss) attributable to Owners of the Company (13) - (14) | C39: 7916.2 | D39: 11544.7 | E39: 15510.6 | F39: 16801.7 | G39: 10994.8
A40: 16 | B40: Earnings per share (in₹): Face value of ₹ 2 each
B41: Basic and diluted earnings per share | C41: 63.61 | D41: 94.26 | E41: 132.57 | F41: 137.63 | G41: 82.31

Sheet BALANCE SHEET
A1: Alkem Laboratories Ltd.
C3: 2019 | D3: =C3+1 -> 2020 | E3: =D3+1 -> 2021 | F3: =E3+1 -> 2022 | G3: =F3+1 -> 2023
A4: I. | B4: ASSETS
A5: 1 | B5: Non-current assets
A6: a | B6: Property, plant and equipment | C6: 21056.2 | D6: 23062.9 | E6: 22339.3 | F6: 22871 | G6: 20654
A7: b | B7: Right of use assets | C7: 0 | D7: 0 | E7: 0 | F7: 1393.5 | G7: 1378.5
A8: c | B8: Capital work in progress | C8: 4929.6 | D8: 3629.7 | E8: 3932.8 | F8: 3394.8 | G8: 3102.7
A9: d | B9: Goodwill | C9: 231.5 | D9: 259.3 | E9: 3953.9 | F9: 4030.9 | G9: 4131.7
A10: e | B10: Goodwill on Consolidation | C10: 3574.1 | D10: 3725.2 | E10: 0 | F10: 0 | G10: 0
A11: f | B11: Other intangible assets | C11: 442.6 | D11: 2032.7 | E11: 1636.6 | F11: 721.9 | G11: 664.1
A12: g | B12: Intangible assets under development | C12: 0 | D12: 0 | E12: 0 | F12: 0 | G12: 129.7
A13: h | B13: Financial assets
B14: (i) Investments | C14: 957.4 | D14: 915 | E14: 1539.5 | F14: 2316.7 | G14: 3046.1
B15: (ii) Loans | C15: 136.3 | D15: 106.1 | E15: 80.2 | F15: 80.2 | G15: 80.2
B16: (iii) Other financial assets | C16: 462 | D16: 466.8 | E16: 607.9 | F16: 7106.7 | G16: 2952.5
A17: i | B17: Deferred tax assets (net) | C17: 7076.3 | D17: 9325.7 | E17: 11079.1 | F17: 13092.6 | G17: 13025
A18: j | B18: Non-current tax assets (net) | C18: 392.7 | D18: 419.5 | E18: 171.1 | F18: 533.1 | G18: 575.4
A19: k | B19: Other non-current assets | C19: 661.9 | D19: 530.1 | E19: 564 | F19: 796.2 | G19: 529.6
B20: Total non-current assets | C20: 39920.6 | D20: 44473 | E20: 45904.4 | F20: 56337.6 | G20: 50269.5
A21: 2 | B21: Current assets
A22: a | B22: Inventories | C22: 14998.7 | D22: 18188.2 | E22: 23124.4 | F22: 30055.3 | G22: 26075.3
A23: b | B23: Financial assets | I23: ='BALANCE SHEET'!C14+'BALANCE SHEET'!C15+'BALANCE SHEET'!C16+'BALANCE SHEET'!C28+'BALANCE SHEET'!C29+'BALANCE SHEET'!C32+'BALANCE SHEET'!C24 -> 5324.4
B24: (i) Investments | C24: 2278.8 | D24: 1698.9 | E24: 1788.3 | F24: 1393.1 | G24: 3172.1
B25: (ii) Trade receivables | C25: 12484.1 | D25: 16493.6 | E25: 16072.1 | F25: 18846 | G25: 21321.8
B26: (iii) Cash and cash equivalents | C26: 2490.5 | D26: 1759.4 | E26: 1742.2 | F26: 2321.8 | G26: 2738
B27: (iv) Bank balances other than (iii) above | C27: 4125.5 | D27: 9162.7 | E27: 18162.3 | F27: 23464 | G27: 23430.9
B28: (v) Loans | C28: 308 | D28: 279.7 | E28: 187.3 | F28: 202.5 | G28: 67.7
B29: (vi) Other financial assets | C29: 1064.6 | D29: 1931 | E29: 2606 | F29: 1731.5 | G29: 1897.5
A30: c | B30: Other current assets | C30: 4293.8 | D30: 5266 | E30: 5550.1 | F30: 6322.8 | G30: 7360.9
C31: 42044 | D31: 54779.5 | E31: 69232.7 | F31: 84337 | G31: 86064.2
A32: d | B32: Non-current assets held for sale | C32: 117.3 | D32: 180.8 | E32: 55.5 | F32: 17.3 | G32: 1232.6
B33: Total current assets | C33: 42161.3 | D33: 54960.3 | E33: 69288.2 | F33: 84354.3 | G33: 87296.8
B34: TOTAL ASSETS | C34: 82081.9 | D34: 99433.3 | E34: 115192.6 | F34: 140691.9 | G34: 137566.3
A35: II. | B35: II. EQUITY AND LIABILITIES
A36: 1 | B36: Equity
A37: a | B37: (a) Equity share capital | C37: 239.1 | D37: 239.1 | E37: 239.1 | F37: 239.1 | G37: 239.1
A38: b | B38: (b) Other equity | C38: 54154.3 | D38: 61367.6 | E38: 73528.2 | F38: 86139.9 | G38: 90213.8
B39: Equity attributable to owners of the Company | C39: 54393.4 | D39: 61606.7 | E39: 73767.3 | F39: 86379 | G39: 90452.9
A40: c | B40: (c) Non-controlling interest | C40: 1326.1 | D40: 1483 | E40: 1812.8 | F40: 2094.3 | G40: 3897.1
B41: Total Equity | C41: 55719.5 | D41: 63089.7 | E41: 75580.1 | F41: 88473.3 | G41: 94350
A42: 2 | B42: 2 Liabilities
A43: 2a | B43: 2a Non-current liabilities
A44: a | B44: (a) Financial liabilities
B45: (i) Borrowings | C45: 2313 | D45: 1592.4 | E45: 279.3 | F45: 93.8 | G45: 0
B46: (ia) Lease liabilities | C46: 0 | D46: 0 | E46: 697.1 | F46: 664.7 | G46: 703.3
B47: (ii) Other financial liabilities | C47: 0 | D47: 0 | E47: 0 | F47: 0 | G47: 1660.1
A48: b | B48: Provisions | C48: 1737.2 | D48: 2220.4 | E48: 2507.3 | F48: 3327.5 | G48: 3693.6
A49: c | B49: Other non-current liabilities | C49: 133.9 | D49: 97.7 | E49: 88.3 | F49: 79.2 | G49: 88
A50: d | B50: Deferred tax liabilities (net) | C50: 3 | D50: 0 | E50: 0 | F50: 0 | G50: 0
B51: Total non-current liabilities | C51: 4187.1 | D51: 3910.5 | E51: 3572 | F51: 4165.2 | G51: 6145
A52: 2b | B52: Current liabilities
A53: a | B53: Financial liabilities
B54: (i) Borrowings | C54: 6712.7 | D54: 15035.1 | E54: 16727.9 | F54: 25707.4 | G54: 13071.5
B55: (ia) Lease liabilities | C55: 0 | D55: 0 | E55: 215.5 | F55: 216 | G55: 192
B56: (ii) Trade payables
B57: Total outstanding dues of micro enterprises and small enterprises | C57: 606.3 | D57: 1025 | E57: 1189.6 | F57: 924.2 | G57: 1104.6
B58: Total outstanding dues of creditors other than micro and small enterprises | C58: 9016.2 | D58: 8515.5 | E58: 9504.5 | F58: 10809.6 | G58: 10545.7
B59: (iii) Other financial liabilities | C59: 3428.7 | D59: 4519.6 | E59: 4653.9 | F59: 5993.8 | G59: 6326.9
A60: b | B60: Other current liabilities | C60: 852.1 | D60: 1035.1 | E60: 1193.4 | F60: 1503.2 | G60: 1868.9
A61: c | B61: Provisions | C61: 1538.2 | D61: 1847 | E61: 2366.4 | F61: 2736 | G61: 3727.5
A62: d | B62: Current tax liabilities (net) | C62: 21.1 | D62: 455.8 | E62: 189.3 | F62: 163.2 | G62: 234.4
B63: Total current liabilities | C63: 22175.3 | D63: 32433.1 | E63: 36040.5 | F63: 48053.4 | G63: 37071.5
B64: Total liabilities | C64: 26362.4 | D64: 36343.6 | E64: 39612.5 | F64: 52218.6 | G64: 43216.5
B65: TOTAL EQUITY AND LIABILITIES | C65: 82081.9 | D65: 99433.3 | E65: 115192.6 | F65: 140691.9 | G65: 137566.5

Sheet Cash Flow Statement
C3: 2019 | D3: =1+C3 -> 2020 | E3: =1+D3 -> 2021 | F3: =1+E3 -> 2022 | G3: =1+F3 -> 2023
A4: A. | B4: Cash Flow from Operating Activities:
B5: Profit before tax | C5: 9546.6 | D5: 12597.9 | E5: 18421 | F5: 18442.8 | G5: 13047.7
B6: Adjustments for:
B7: Depreciation and amortisation expense | C7: 1931.8 | D7: 2527.6 | E7: 2745.8 | F7: 3039.6 | G7: 3104.2
B8: Liabilities no longer required written back | C8: 0 | D8: 0 | E8: 0 | F8: -160.1 | G8: -17.5
B9: Profit on sale of investments | C9: -73.3 | D9: -0.8 | E9: -102.6 | F9: -33.8 | G9: -21.6
B10: Unrealised (gain) / loss on fair valuation of investments (net) | C10: 45.5 | D10: 172.2 | E10: -266.9 | F10: 69 | G10: -287
B11: Profit on sale of property plant and equipment (net) | C11: 54.8 | D11: -12.6 | E11: -37 | F11: 14.3 | G11: 123.6
B12: Employee stock compensation expenses | C12: 5.8 | D12: 1.5 | E12: 1.1 | F12: 0 | G12: 0
B13: Recovery of Bad debts | C13: 0 | D13: 0 | E13: -114.9 | F13: 0 | G13: 0
B14: Unrealised foreign currency (gain) / loss on revaluation (net) | C14: -113.8 | D14: -275.4 | E14: 9.7 | F14: -177 | G14: -118.8
B15: Dividend Income | C15: -1.2 | D15: -1.1 | E15: -0.2 | F15: -1.9 | G15: -1.9
B16: Profit on sale of brand (net) | C16: 0 | D16: 0 | E16: -351 | F16: 0 | G16: 0
B17: Impairment loss on property, plant and equipment | C17: 0 | D17: 32.7 | E17: 0 | F17: 11.2 | G17: 1051.5
B18: Interest Income | C18: -412.8 | D18: -631.2 | E18: -901.2 | F18: -1226.8 | G18: -1711.4
... B20: Allowances for doubtful debts | C20: 185.9 | D20: 101.7 | E20: 82.8 | F20: 27.8 | G20: 48.8
B21: Rent income | C21: -5.3 | D21: -6.5 | E21: -8.4
B22: Subtotal of Adjustments | C22: 2163.7 | D22: 2558.7 | E22: =SUM(E7:E21) -> 1646.4 | F22: 2086 | G22: 3243.5
B23: Operating profit before working capital changes | C23: 11710.3 | D23: 15156.6 | E23: 20067.4 | F23: 20528.8 | G23: 16291.2
B24: Adjustments for changes in working capital:
B25: (Increase) in trade receivables | C25: -1558.5 | D25: -2574.4 | E25: -257.6 | F25: -2217.5 | G25: -1347.1
B26: (Increase) / Decrease in loans, other financial assets and other assets | C26: 156.8 | D26: -1538 | E26: -926.5 | F26: -435.8 | G26: -770.1
B27: (Increase) Decrease in inventories | C27: -373 | D27: -2817.4 | E27: -4977 | F27: -6731.4 | G27: 4734.1
B28: Increase / (Decrease) in trade payable, other financial liabilities and other liabilities | C28: -109.5 | D28: -37.4 | E28: 2124.2 | F28: 3344.9 | G28: 145.1
B29: Increase in provisions | C29: 481.5 | D29: 495.2 | E29: 625.3 | F29: 590.2 | G29: 505.7
B30: Subtotal of adjustments | C30: -1402.7 | D30: -6472 | E30: -3411.6 | F30: -5449.6 | G30: 3267.7
B31: Cash generated from operations | C31: 10307.6 | D31: 8684.6 | E31: 16655.8 | F31: 15079.2 | G31: 19558.9
B32: Less: Income taxes paid (net of refund) | C32: -2511.1 | D32: -2833.8 | E32: -4006.8 | F32: -3969 | G32: -2733.9
B33: Net Cash generated from operating activities | C33: 7796.5 | D33: 5850.8 | E33: 12649 | F33: 11110.2 | G33: 16825
A34: B. | B34: Cash Flow from Investing Activities:
B35: Purchases of property, plant and equipment | C35: -5291.6 | D35: -3630.9 | E35: -1949.1 | F35: -3388.8 | G35: -2329.1
B36: Sale of property, plant and equipment | C36: 22.3 | D36: 154.5 | E36: 104.6 | F36: 109 | G36: 32
B37: (Purchase of) / Proceeds from sale of investments (net) | C37: 1234.7 | D37: 457.5 | E37: -348.3 | F37: -409.3 | G37: -2175.3
B38: Profit on sale of brand (net) | C38: 0 | D38: 0 | E38: 351 | F38: 0 | G38: 0
B39: (Investment made in) / Redemption of bank deposits having maturity of more than 3 months (net) | C39: 427.5 | D39: -4911.4 | E39: -8937.9 | F39: -11641.8 | G39: 4129.8
B40: Dividend received | C40: 1.2 | D40: 1.1 | E40: 0.2 | F40: 1.9 | G40: 1.9
B41: Interest received | C41: 436.7 | D41: 509.2 | E41: 785.7 | F41: 977.7 | G41: 1469.1
B42: Rent received | C42: 5.3 | D42: 6.5 | E42: 8.4 | F42: 0 | G42: 0
B43: Net cash generated from / (used in) investing activities | C43: -3163.9 | D43: -7413.5 | E43: -9985.4 | F43: -14351.3 | G43: 1128.4
A44: C. | B44: Cash Flow from Financing Activities:
B45: Repayment of non-current borrowings (net) | C45: -70.6 | D45: -1810.5 | E45: -387.4 | F45: -192.9 | G45: -95
B46: Proceeds from current borrowings (net) | C46: -986.7 | D46: 7841.2 | E46: 1784.2 | F46: 8820.7 | G46: -12689.8
B47: Proceeds from issue of compulsory convertible preferance shares | C47: 0 | D47: 0 | E47: 0 | F47: 0 | G47: 1614.8
B48: Dividends paid | C48: -2185.8 | D48: -4395.6 | E48: -3347.8 | F48: -4219.1 | G48: -5295.2 | I48: -
B49: Repayment of lease liabilities (net) | C49: 0 | D49: -193 | E49: -230.3 | F49: -211.7 | G49: -238.4
B50: Interest paid | C50: -546.3 | D50: -650.6 | E50: -536.2 | F50: -401.3 | G50: -904.6
B51: Net cash (used in)/generated from financing activities | C51: -3789.4 | D51: 791.5 | E51: -2717.5 | F51: 3795.7 | G51: -17608.2
A52: D. | B52: Net (decrease)/increase in cash and cash equivalents (A+B+C) | C52: 843.2 | D52: -771.2 | E52: -53.9 | F52: =F51+F43+F33 -> 554.6 | G52: =G51+G43+G33 -> 345.2
A53: E. | B53: Cash and cash equivalents as at beginning of the year | C53: 1667.1 | D53: 2490.5 | E53: 1759.4 | F53: 1742.2 | G53: 2321.8
B54: Add/Less: Effect of exchange difference on foreign currency cash and cash equivalents | C54: -19.8 | D54: 40.1 | E54: 36.7 | F54: 25 | G54: 71
A55: F. | B55: Cash and cash equivalents as at end of the year (D+E) | C55: 2490.5 | D55: 1759.4 | E55: 1742.2 | F55: 2321.8 | G55: 2738

Sheet Model
A1: Alkem Laboratories LTD | F1: Historical Period | M1: Forecasting Period
A2: Financial Statement & DCF Analysis | H2: 2019 | I2: =H2+1 -> 2020 | J2: =I2+1 -> 2021 | K2: =J2+1 -> 2022 | L2: =K2+1 -> 2023 | M2: =L2+1 -> 2024 | N2: =M2+1 -> 2025 | O2: =N2+1 -> 2026 | P2: =O2+1 -> 2027 | Q2: =P2+1 -> 2028
D3: Master check | H3: =IF(H73>1,"Error","OK") -> OK | I3: =IF(I73>1,"Error","OK") -> OK | J3: =IF(J73>1,"Error","OK") -> OK | K3: =IF(K73>1,"Error","OK") -> OK | L3: =IF(L73>1,"Error","OK") -> OK | M3: =IF(M73>1,"Error","OK") -> OK | N3: =IF(N73>1,"Error","OK") -> OK | O3: =IF(O73>1,"Error","OK") -> OK | ... Q3: =IF(Q73>1,"Error","OK") -> OK
A5: Ratio & Assumptions
D7: Scenario | E7: Bear Case | F7: Units | G7: =IF(E7=Scenario!D5,1,IF(Model!E7=Scenario!D6,2,3)) -> 3
D8: Revenue Growth Rate | F8: % | I8: =I25/H25-1 -> 0.13417759 | J8: =J25/I25-1 -> 0.062395438 | K8: =K25/J25-1 -> 0.19956887 | L8: =L25/K25-1 -> 0.090751623 | M8: {=CHOOSE(G7,Scenario!H5:L5,Scenario!H6:L6,Scenario!H7:L7)} -> 0.062395438 | N8: 0.053036123 | O8: 0.045080704 | P8: 0.038318599 | Q8: 0.032570809
D9: COGS (% of Revenue) | F9: % | H9: =-(H26/H25) -> 0.40028462 | I9: =-(I26/I25) -> 0.40086238 | J9: =-(J26/J25) -> 0.39463689 | K9: =-(K26/K25) -> 0.39309905 | L9: =-(L26/L25) -> 0.42303043 | M9: =AVERAGE(H9:L9) -> 0.40238268 | N9: =M9 -> 0.40238268 | O9: =N9 -> 0.40238268 | P9: =O9 -> 0.40238268 | Q9: =P9 -> 0.40238268
D10: Salary (% of Revenue) | F10: % | H10: =-H29/H25 -> 0.18518755 | I10: =-I29/I25 -> 0.18042007 | J10: =-J29/J25 -> 0.1828571 | K10: =-K29/K25 -> 0.18456601 | L10: =-L29/L25 -> 0.18374879 | M10: =AVERAGE(H10:L10) -> 0.1833559 | N10: =M10 -> 0.1833559 | O10: =N10 -> 0.1833559 | P10: =O10 -> 0.1833559 | Q10: =P10 -> 0.1833559
D11: Other SG&A (% of Revenue) | F11: % | H11: =-H30/H25 -> 0.26300666 | I11: =-I30/I25 -> 0.24214439 | J11: =-J30/J25 -> 0.20339853 | K11: =-K30/K25 -> 0.22928592 | L11: =-L30/L25 -> 0.25446623 | M11: =AVERAGE(H11:L11) -> 0.23846035 | N11: =M11 -> 0.23846035 | O11: =N11 -> 0.23846035 | P11: =O11 -> 0.23846035 | Q11: =P11 -> 0.23846035
D12: Depreciation & Amortization (% of PPE) | F12: % | I12: =-I32/I118 -> 0.095639539 | J12: =-J32/J118 -> 0.09558821 | K12: =-K32/K118 -> 0.10891227 | L12: =-L32/L118 -> 0.10937522 | M12: =AVERAGE(H12:L12) -> 0.10237881 | N12: =M12 -> 0.10237881 | O12: =N12 -> 0.10237881 | P12: =O12 -> 0.10237881 | Q12: =P12 -> 0.10237881
D13: Interest (% of debt) | F13: % | I13: =-I34/I124 -> 0.072083052 | J13: =-J34/J124 -> 0.035435273 | K13: =-K34/K124 -> 0.029224657 | L13: =-L34/L124 -> 0.040237015 | M13: =AVERAGE(H13:L13) -> 0.044244999 | N13: =M13 -> 0.044244999 | O13: =N13 -> 0.044244999 | P13: =O13 -> 0.044244999 | Q13: =P13 -> 0.044244999
D14: Other Income (Expenses)(% of Revenue) | F14: % | H14: =H35/H25 -> 0.011920312 | I14: =I35/I25 -> 0.012489873 | J14: =J35/J25 -> 0.026306795 | K14: =K35/K25 -> 0.013888223 | L14: =L35/L25 -> 0.009750622 | M14: =AVERAGE(H14:L14) -> 0.014871165 | N14: =M14 -> 0.014871165 | O14: =N14 -> 0.014871165 | P14: =O14 -> 0.014871165 | Q14: =P14 -> 0.014871165
D15: Taxes Rate (% of Earning Before Tax) | F15: % | H15: =-H37/H36 -> 0.18961725 | I15: =-I37/I36 -> 0.087697156 | J15: =-J37/J36 -> 0.12177949 | K15: =-K37/K36 -> 0.088901902 | L15: =-L37/L36 -> 0.22836209 | M15: =AVERAGE(H15:L15) -> 0.14327158 | N15: =M15 -> 0.14327158 | O15: =N15 -> 0.14327158 | P15: =O15 -> 0.14327158 | Q15: =P15 -> 0.14327158
D16: Divident Payout Ratio | F16: % | H16: =-H98/H38 -> 0.28253451 | I16: =-I98/I38 -> 0.38245556 | J16: =-J98/J38 -> 0.20693918 | K16: =-K98/K38 -> 0.25108908 | L16: =-L98/L38 -> 0.52593836 | M16: =AVERAGE(H16:L16) -> 0.32979134 | N16: =M16 -> 0.32979134 | O16: =N16 -> 0.32979134 | P16: =O16 -> 0.32979134 | Q16: =P16 -> 0.32979134
D17: Account Recievable | F17: Days | H17: =H47/H25*365 -> 61.935284 | I17: =I47/I25*365 -> 72.146504 | J17: =J47/J25*365 -> 66.173828 | K17: =K47/K25*365 -> 64.685604 | L17: =L47/L25*365 -> 67.094427 | M17: =AVERAGE(H17:L17) -> 66.407129 | N17: =M17 -> 66.407129 | O17: =N17 -> 66.407129 | P17: =O17 -> 66.407129 | Q17: =P17 -> 66.407129
D18: Inventory | F18: Days | H18: =-H48/H26*365 -> 185.8941 | I18: =-I48/I26*365 -> 198.46972 | J18: =-J48/J26*365 -> 241.26061 | K18: =-K48/K26*365 -> 262.4264 | L18: =-L48/L26*365 -> 193.96362 | M18: =AVERAGE(H18:L18) -> 216.40289 | N18: =M18 -> 216.40289 | O18: =N18 -> 216.40289 | P18: =O18 -> 216.40289 | Q18: =P18 -> 216.40289
D19: Account Payable | F19: Days | H19: =-H60/H26*365 -> 119.2614 | I19: =-I60/I26*365 -> 104.10598 | J19: =-J60/J26*365 -> 111.57328 | K19: =-K60/K26*365 -> 102.45311 | L19: =-L60/L26*365 -> 86.661874 | M19: =AVERAGE(H19:L19) -> 104.81113 | N19: =M19 -> 104.81113 | O19: =N19 -> 104.81113 | P19: =O19 -> 104.81113 | Q19: =P19 -> 104.81113
D20: Capital Asset Turnover Ratio | F20: Times | H20: =H25/H52 -> 2.7838197 | I20: =I25/I52 -> 2.9048818 | J20: =J25/J52 -> 3.1764324 | K20: =K25/K52 -> 3.7469134 | L20: =L25/L52 -> 4.4734699 | M20: =L20+0.5 -> 4.9734699 | N20: =M20+0.5 -> 5.4734699 | O20: =N20+0.5 -> 5.9734699 | P20: =O20+0.5 -> 6.4734699 | Q20: =P20+0.5 -> 6.9734699
A23: Income Statement
B24: Income
D25: Revenue | F25: ₹ in MM | H25: ='PL Statement'!C5 -> 73571.9 | I25: ='PL Statement'!D5 -> 83443.6 | J25: ='PL Statement'!E5 -> 88650.1 | K25: ='PL Statement'!F5 -> 106341.9 | L25: ='PL Statement'!G5 -> 115992.6 | M25: =L25*(1+M8) -> 123230.01 | N25: =M25*(1+N8) -> 129765.65 | O25: =N25*(1+O8) -> 135615.58 | P25: =O25*(1+P8) -> 140812.18 | Q25: =P25*(1+Q8) -> 145398.54
D26: Cost of Good Solds (COGS) | F26: ₹ in MM | H26: =-('PL Statement'!C9+'PL Statement'!C10+'PL Statement'!C11) -> -29449.7 | I26: =-('PL Statement'!D9+'PL Statement'!D10+'PL Statement'!D11) -> -33449.4 | J26: =-('PL Statement'!E9+'PL Statement'!E10+'PL Statement'!E11) -> -34984.6 | K26: =-('PL Statement'!F9+'PL Statement'!F10+'PL Statement'!F11) -> -41802.9 | L26: =-('PL Statement'!G9+'PL Statement'!G10+'PL Statement'!G11) -> -49068.4 | M26: =-M25*M9 -> -49585.621 | N26: =-N25*N9 -> -52215.45 | O26: =-O25*O9 -> -54569.359 | P26: =-P25*P9 -> -56660.38 | Q26: =-Q25*Q9 -> -58505.855
D27: Gross Profit | F27: ₹ in MM | H27: =SUM(H25:H26) -> 44122.2 | I27: =SUM(I25:I26) -> 49994.2 | J27: =SUM(J25:J26) -> 53665.5 | K27: =SUM(K25:K26) -> 64539 | L27: =SUM(L25:L26) -> 66924.2 | M27: =SUM(M25:M26) -> 73644.388 | N27: =SUM(N25:N26) -> 77550.201 | O27: =SUM(O25:O26) -> 81046.219 | ... Q27: =SUM(Q25:Q26) -> 86892.688
B28: Expenses
D29: Salaries & Benefits | F29: ₹ in MM | H29: =-('PL Statement'!C12) -> -13624.6 | I29: =-('PL Statement'!D12) -> -15054.9 | J29: =-('PL Statement'!E12) -> -16210.3 | K29: =-('PL Statement'!F12) -> -19627.1 | L29: =-('PL Statement'!G12) -> -21313.5 | M29: =-M25*M10 -> -22594.95 | N29: =-N25*N10 -> -23793.298 | O29: =-O25*O10 -> -24865.917 | P29: =-P25*P10 -> -25818.744 | Q29: =-Q25*Q10 -> -26659.681
D30: Other SG&A Expenses | F30: ₹ in MM | H30: =-('PL Statement'!C15) -> -19349.9 | I30: =-('PL Statement'!D15) -> -20205.4 | J30: =-('PL Statement'!E15) -> -18031.3 | K30: =-('PL Statement'!F15) -> -24382.7 | L30: =-('PL Statement'!G15) -> -29516.2 | M30: =-M25*M11 -> -29385.471 | N30: =-N25*N11 -> -30943.962 | O30: =-O25*O11 -> -32338.938 | P30: =-P25*P11 -> -33578.121 | Q30: =-Q25*Q11 -> -34671.787
D31: EBITDA | F31: ₹ in MM | H31: =SUM(H27:H30) -> 11147.7 | I31: =SUM(I27:I30) -> 14733.9 | J31: =SUM(J27:J30) -> 19423.9 | K31: =SUM(K27:K30) -> 20529.2 | L31: =SUM(L27:L30) -> 16094.5 | M31: =SUM(M27:M30) -> 21663.968 | N31: =SUM(N27:N30) -> 22812.941 | O31: =SUM(O27:O30) -> 23841.364 | ... Q31: =SUM(Q27:Q30) -> 25561.22
D32: Depreciation & Amortization Expenses | F32: ₹ in MM | H32: =-'PL Statement'!C14 -> -1931.8 | I32: =-'PL Statement'!D14 -> -2527.6 | J32: =-'PL Statement'!E14 -> -2745.8 | K32: =-'PL Statement'!F14 -> -3039.6 | L32: =-'PL Statement'!G14 -> -3104.2 | M32: =M120 -> -2654.5802 | N32: =N120 -> -2531.7894 | O32: =O120 -> -2394.8341 | P32: =P120 -> -2249.9152 | Q32: =Q120 -> -2101.7565
D33: EBIT | F33: ₹ in MM | H33: =SUM(H31:H32) -> 9215.9 | I33: =SUM(I31:I32) -> 12206.3 | J33: =SUM(J31:J32) -> 16678.1 | K33: =SUM(K31:K32) -> 17489.6 | L33: =SUM(L31:L32) -> 12990.3 | M33: =SUM(M31:M32) -> 19009.388 | N33: =SUM(N31:N32) -> 20281.151 | O33: =SUM(O31:O32) -> 21446.53 | ... Q33: =SUM(Q31:Q32) -> 23459.464
D34: Interest | F34: ₹ in MM | H34: =-'PL Statement'!C13 -> -546.3 | I34: =-'PL Statement'!D13 -> -650.6 | J34: =-'PL Statement'!E13 -> -589.2 | K34: =-'PL Statement'!F13 -> -523.7 | L34: =-'PL Statement'!G13 -> -1073.6 | M34: =M127 -> -617.96105 | N34: =N127 -> -617.96105 | O34: =O127 -> -617.96105 | P34: =P127 -> -617.96105 | Q34: =Q127 -> -617.96105
D35: Other Income (Expenses) | F35: ₹ in MM | H35: ='PL Statement'!C6+'PL Statement'!C18 -> 877 | I35: ='PL Statement'!D6+'PL Statement'!D18 -> 1042.2 | J35: ='PL Statement'!E6+'PL Statement'!E18 -> 2332.1 | K35: ='PL Statement'!F6+'PL Statement'!F18 -> 1476.9 | L35: ='PL Statement'!G6+'PL Statement'!G18 -> 1131 | M35: =M25*M14 -> 1832.5738 | N35: =N25*N14 -> 1929.7664 | O35: =O25*O14 -> 2016.7616 | P35: =P25*P14 -> 2094.0411 | Q35: =Q25*Q14 -> 2162.2457
D36: Earning Before Tax | F36: ₹ in MM | H36: =SUM(H33:H35) -> 9546.6 | I36: =SUM(I33:I35) -> 12597.9 | J36: =SUM(J33:J35) -> 18421 | K36: =SUM(K33:K35) -> 18442.8 | L36: =SUM(L33:L35) -> 13047.7 | M36: =SUM(M33:M35) -> 20224 | N36: =SUM(N33:N35) -> 21592.957 | O36: =SUM(O33:O35) -> 22845.331 | ... Q36: =SUM(Q33:Q35) -> 25003.748
D37: Taxes | F37: ₹ in MM | H37: =-'PL Statement'!C25 -> -1810.2 | I37: =-'PL Statement'!D25 -> -1104.8 | J37: =-'PL Statement'!E25 -> -2243.3 | K37: =-'PL Statement'!F25 -> -1639.6 | L37: =-'PL Statement'!G25 -> -2979.6 | M37: =-M36*M15 -> -2897.5244 | N37: =-N36*N15 -> -3093.6569 | O37: =-O36*O15 -> -3273.0865 | P37: =-P36*P15 -> -3435.8095 | Q37: =-Q36*Q15 -> -3582.3264
D38: Net Earing | F38: ₹ in MM | H38: =SUM(H36:H37) -> 7736.4 | I38: =SUM(I36:I37) -> 11493.1 | J38: =SUM(J36:J37) -> 16177.7 | K38: =SUM(K36:K37) -> 16803.2 | L38: =SUM(L36:L37) -> 10068.1 | M38: =SUM(M36:M37) -> 17326.476 | N38: =SUM(N36:N37) -> 18499.3 | O38: =SUM(O36:O37) -> 19572.244 | ... Q38: =SUM(Q36:Q37) -> 21421.422
A41: Balance Sheet
B43: Asset
C44: Current Asset :
D45: Cash | F45: ₹ in MM | H45: ='BALANCE SHEET'!C26 -> 2490.5 | I45: ='BALANCE SHEET'!D26 -> 1759.4 | J45: ='BALANCE SHEET'!E26 -> 1742.2 | K45: ='BALANCE SHEET'!F26 -> 2321.8 | L45: ='BALANCE SHEET'!G26 -> 2738 | M45: =M104 -> 13716.537 | N45: =N104 -> 25459.562 | O45: =O104 -> 38208.583 | P45: =P104 -> 51840.629 | Q45: =Q104 -> 66242.87
D46: Bank Deposits | F46: ₹ in MM | H46: ='BALANCE SHEET'!C27 -> 4125.5 | I46: ='BALANCE SHEET'!D27 -> 9162.7 | J46: ='BALANCE SHEET'!E27 -> 18162.3 | K46: ='BALANCE SHEET'!F27 -> 23464 | L46: ='BALANCE SHEET'!G27 -> 23430.9 | M46: =L46 -> 23430.9 | N46: =M46 -> 23430.9 | O46: =N46 -> 23430.9 | P46: =O46 -> 23430.9 | Q46: =P46 -> 23430.9
D47: Account Receivable | F47: ₹ in MM | H47: ='BALANCE SHEET'!C25 -> 12484.1 | I47: ='BALANCE SHEET'!D25 -> 16493.6 | J47: ='BALANCE SHEET'!E25 -> 16072.1 | K47: ='BALANCE SHEET'!F25 -> 18846 | L47: ='BALANCE SHEET'!G25 -> 21321.8 | M47: =M25*M17/365 -> 22420.14 | N47: =N25*N17/365 -> 23609.217 | O47: =O25*O17/365 -> 24673.538 | P47: =P25*P17/365 -> 25618.993 | Q47: =Q25*Q17/365 -> 26453.424
D48: Inventory | F48: ₹ in MM | H48: ='BALANCE SHEET'!C22 -> 14998.7 | I48: ='BALANCE SHEET'!D22 -> 18188.2 | J48: ='BALANCE SHEET'!E22 -> 23124.4 | K48: ='BALANCE SHEET'!F22 -> 30055.3 | L48: ='BALANCE SHEET'!G22 -> 26075.3 | M48: =-M26*M18/365 -> 29398.552 | N48: =-N26*N18/365 -> 30957.738 | O48: =-O26*O18/365 -> 32353.334 | P48: =-P26*P18/365 -> 33593.069 | Q48: =-Q26*Q18/365 -> 34687.222
D49: Other Current Assets | F49: ₹ in MM | H49: ='BALANCE SHEET'!C30 -> 4293.8 | I49: ='BALANCE SHEET'!D30 -> 5266 | J49: ='BALANCE SHEET'!E30 -> 5550.1 | K49: ='BALANCE SHEET'!F30 -> 6322.8 | L49: ='BALANCE SHEET'!G30 -> 7360.9 | M49: =L49 -> 7360.9 | N49: =M49 -> 7360.9 | O49: =N49 -> 7360.9 | P49: =O49 -> 7360.9 | Q49: =P49 -> 7360.9
C51: Non Current Assets :
D52: Property & equipment | F52: ₹ in MM | H52: ='BALANCE SHEET'!C6+'BALANCE SHEET'!C7+'BALANCE SHEET'!C8+'BALANCE SHEET'!C11+'BALANCE SHEET'!C12 -> 26428.4 | I52: ='BALANCE SHEET'!D6+'BALANCE SHEET'!D7+'BALANCE SHEET'!D8+'BALANCE SHEET'!D11+'BALANCE SHEET'!D12 -> 28725.3 | J52: ='BALANCE SHEET'!E6+'BALANCE SHEET'!E7+'BALANCE SHEET'!E8+'BALANCE SHEET'!E11+'BALANCE SHEET'!E12 -> 27908.7 | K52: ='BALANCE SHEET'!F6+'BALANCE SHEET'!F7+'BALANCE SHEET'!F8+'BALANCE SHEET'!F11+'BALANCE SHEET'!F12 -> 28381.2 | L52: ='BALANCE SHEET'!G6+'BALANCE SHEET'!G7+'BALANCE SHEET'!G8+'BALANCE SHEET'!G11+'BALANCE SHEET'!G12 -> 25929 | M52: =M121 -> 24729.623 | N52: =N121 -> 23391.892 | O52: =O121 -> 21976.376 | P52: =P121 -> 20529.214 | Q52: =Q121 -> 19085.145
D53: Godwill | F53: ₹ in MM | H53: ='BALANCE SHEET'!C9+'BALANCE SHEET'!C10 -> 3805.6 | I53: ='BALANCE SHEET'!D9+'BALANCE SHEET'!D10 -> 3984.5 | J53: ='BALANCE SHEET'!E9+'BALANCE SHEET'!E10 -> 3953.9 | K53: ='BALANCE SHEET'!F9+'BALANCE SHEET'!F10 -> 4030.9 | L53: ='BALANCE SHEET'!G9+'BALANCE SHEET'!G10 -> 4131.7 | M53: =L53 -> 4131.7 | N53: =M53 -> 4131.7 | O53: =N53 -> 4131.7 | P53: =O53 -> 4131.7 | Q53: =P53 -> 4131.7
D54: Financial Assets | F54: ₹ in MM | H54: ='BALANCE SHEET'!C14+'BALANCE SHEET'!C15+'BALANCE SHEET'!C16+'BALANCE SHEET'!C28+'BALANCE SHEET'!C29+'BALANCE SHEET'!C32+'BALANCE SHEET'!C24 -> 5324.4 | I54: ='BALANCE SHEET'!D14+'BALANCE SHEET'!D15+'BALANCE SHEET'!D16+'BALANCE SHEET'!D28+'BALANCE SHEET'!D29+'BALANCE SHEET'!D32+'BALANCE SHEET'!D24 -> 5578.3 | J54: ='BALANCE SHEET'!E14+'BALANCE SHEET'!E15+'BALANCE SHEET'!E16+'BALANCE SHEET'!E28+'BALANCE SHEET'!E29+'BALANCE SHEET'!E32+'BALANCE SHEET'!E24 -> 6864.7 | K54: ='BALANCE SHEET'!F14+'BALANCE SHEET'!F15+'BALANCE SHEET'!F16+'BALANCE SHEET'!F28+'BALANCE SHEET'!F29+'BALANCE SHEET'!F32+'BALANCE SHEET'!F24 -> 12848 | L54: ='BALANCE SHEET'!G14+'BALANCE SHEET'!G15+'BALANCE SHEET'!G16+'BALANCE SHEET'!G28+'BALANCE SHEET'!G29+'BALANCE SHEET'!G32+'BALANCE SHEET'!G24 -> 12448.7 | M54: =L54 -> 12448.7 | N54: =M54 -> 12448.7 | O54: =N54 -> 12448.7 | P54: =O54 -> 12448.7 | Q54: =P54 -> 12448.7
D55: Other Non Current Assets | F55: ₹ in MM | H55: ='BALANCE SHEET'!C17+'BALANCE SHEET'!C18+'BALANCE SHEET'!C19 -> 8130.9 | I55: ='BALANCE SHEET'!D17+'BALANCE SHEET'!D18+'BALANCE SHEET'!D19 -> 10275.3 | J55: ='BALANCE SHEET'!E17+'BALANCE SHEET'!E18+'BALANCE SHEET'!E19 -> 11814.2 | K55: ='BALANCE SHEET'!F17+'BALANCE SHEET'!F18+'BALANCE SHEET'!F19 -> 14421.9 | L55: ='BALANCE SHEET'!G17+'BALANCE SHEET'!G18+'BALANCE SHEET'!G19 -> 14130 | M55: =L55 -> 14130 | N55: =M55 -> 14130 | O55: =N55 -> 14130 | P55: =O55 -> 14130 | Q55: =P55 -> 14130
D56: Total Assets | F56: ₹ in MM | H56: =SUM(H45:H55) -> 82081.9 | I56: =SUM(I45:I55) -> 99433.3 | J56: =SUM(J45:J55) -> 115192.6 | K56: =SUM(K45:K55) -> 140691.9 | L56: =SUM(L45:L55) -> 137566.3 | M56: =SUM(M45:M55) -> 151767.05 | N56: =SUM(N45:N55) -> 164920.61 | O56: =SUM(O45:O55) -> 178714.03 | ... Q56: =SUM(Q45:Q55) -> 207970.86
B58: Liabilities
C59: Current Liabilities :
D60: Account Payable | F60: ₹ in MM | H60: ='BALANCE SHEET'!C57+'BALANCE SHEET'!C58 -> 9622.5 | I60: ='BALANCE SHEET'!D57+'BALANCE SHEET'!D58 -> 9540.5 | J60: ='BALANCE SHEET'!E57+'BALANCE SHEET'!E58 -> 10694.1 | K60: ='BALANCE SHEET'!F57+'BALANCE SHEET'!F58 -> 11733.8 | L60: ='BALANCE SHEET'!G57+'BALANCE SHEET'!G58 -> 11650.3 | M60: =-M26*M19/365 -> 14238.698 | N60: =-N26*N19/365 -> 14993.864 | O60: =-O26*O19/365 -> 15669.797 | P60: =-P26*P19/365 -> 16270.242 | Q60: =-Q26*Q19/365 -> 16800.177
D61: Other Current Liabilities | F61: ₹ in MM | H61: ='BALANCE SHEET'!C59+'BALANCE SHEET'!C60+'BALANCE SHEET'!C61+'BALANCE SHEET'!C62 -> 5840.1 | I61: ='BALANCE SHEET'!D59+'BALANCE SHEET'!D60+'BALANCE SHEET'!D61+'BALANCE SHEET'!D62 -> 7857.5 | J61: ='BALANCE SHEET'!E59+'BALANCE SHEET'!E60+'BALANCE SHEET'!E61+'BALANCE SHEET'!E62 -> 8403 | K61: ='BALANCE SHEET'!F59+'BALANCE SHEET'!F60+'BALANCE SHEET'!F61+'BALANCE SHEET'!F62 -> 10396.2 | L61: ='BALANCE SHEET'!G59+'BALANCE SHEET'!G60+'BALANCE SHEET'!G61+'BALANCE SHEET'!G62 -> 12157.7 | M61: =L61 -> 12157.7 | N61: =M61 -> 12157.7 | O61: =N61 -> 12157.7 | P61: =O61 -> 12157.7 | Q61: =P61 -> 12157.7
C62: Non- Current Liabilities | F62: ₹ in MM
D63: Debt | F63: ₹ in MM | H63: ='BALANCE SHEET'!C54+'BALANCE SHEET'!C55+'BALANCE SHEET'!C45+'BALANCE SHEET'!C46 -> 9025.7 | I63: ='BALANCE SHEET'!D54+'BALANCE SHEET'!D55+'BALANCE SHEET'!D45+'BALANCE SHEET'!D46 -> 16627.5 | J63: ='BALANCE SHEET'!E54+'BALANCE SHEET'!E55+'BALANCE SHEET'!E45+'BALANCE SHEET'!E46 -> 17919.8 | K63: ='BALANCE SHEET'!F54+'BALANCE SHEET'!F55+'BALANCE SHEET'!F45+'BALANCE SHEET'!F46 -> 26681.9 | L63: ='BALANCE SHEET'!G54+'BALANCE SHEET'!G55+'BALANCE SHEET'!G45+'BALANCE SHEET'!G46 -> 13966.8 | M63: =M126 -> 13966.8 | N63: =N126 -> 13966.8 | O63: =O126 -> 13966.8 | P63: =P126 -> 13966.8 | Q63: =Q126 -> 13966.8
D64: Other Non Current Liabilities | F64: ₹ in MM | H64: ='BALANCE SHEET'!C47+'BALANCE SHEET'!C48+'BALANCE SHEET'!C49+'BALANCE SHEET'!C50 -> 1874.1 | I64: ='BALANCE SHEET'!D47+'BALANCE SHEET'!D48+'BALANCE SHEET'!D49+'BALANCE SHEET'!D50 -> 2318.1 | J64: ='BALANCE SHEET'!E47+'BALANCE SHEET'!E48+'BALANCE SHEET'!E49+'BALANCE SHEET'!E50 -> 2595.6 | K64: ='BALANCE SHEET'!F47+'BALANCE SHEET'!F48+'BALANCE SHEET'!F49+'BALANCE SHEET'!F50 -> 3406.7 | L64: ='BALANCE SHEET'!G47+'BALANCE SHEET'!G48+'BALANCE SHEET'!G49+'BALANCE SHEET'!G50 -> 5441.7 | M64: =L64 -> 5441.7 | N64: =M64 -> 5441.7 | O64: =N64 -> 5441.7 | P64: =O64 -> 5441.7 | Q64: =P64 -> 5441.7
D65: Total Liabilities | F65: ₹ in MM | H65: =SUM(H60:H64) -> 26362.4 | I65: =SUM(I60:I64) -> 36343.6 | J65: =SUM(J60:J64) -> 39612.5 | K65: =SUM(K60:K64) -> 52218.6 | L65: =SUM(L60:L64) -> 43216.5 | M65: =SUM(M60:M64) -> 45804.898 | N65: =SUM(N60:N64) -> 46560.064 | O65: =SUM(O60:O64) -> 47235.997 | ... Q65: =SUM(Q60:Q64) -> 48366.377
C66: Shareholder Equity
D67: Equity Capital | F67: ₹ in MM | H67: ='BALANCE SHEET'!C37 -> 239.1 | I67: ='BALANCE SHEET'!D37 -> 239.1 | J67: ='BALANCE SHEET'!E37 -> 239.1 | K67: ='BALANCE SHEET'!F37 -> 239.1 | L67: ='BALANCE SHEET'!G37 -> 239.1 | M67: =L67 -> 239.1 | N67: =M67 -> 239.1 | O67: =N67 -> 239.1 | P67: =O67 -> 239.1 | Q67: =P67 -> 239.1
D68: Retained Earning | F68: ₹ in MM | H68: ='BALANCE SHEET'!C38 -> 54154.3 | I68: ='BALANCE SHEET'!D38 -> 61367.6 | J68: ='BALANCE SHEET'!E38 -> 73528.2 | K68: ='BALANCE SHEET'!F38 -> 86139.9 | L68: ='BALANCE SHEET'!G38 -> 90213.8 | M68: =L68+M38+M98 -> 101826.15 | N68: =M68+N38+N98 -> 114224.55 | O68: =N68+O38+O98 -> 127342.03 | P68: =O68+P38+P98 -> 141111.66 | Q68: =P68+Q38+Q98 -> 155468.48
D69: Total Shareholder Equity | F69: ₹ in MM | H69: =SUM(H67:H68) -> 54393.4 | I69: =SUM(I67:I68) -> 61606.7 | J69: =SUM(J67:J68) -> 73767.3 | K69: =SUM(K67:K68) -> 86379 | L69: =SUM(L67:L68) -> 90452.9 | M69: =SUM(M67:M68) -> 102065.25 | N69: =SUM(N67:N68) -> 114463.65 | O69: =SUM(O67:O68) -> 127581.13 | ... Q69: =SUM(Q67:Q68) -> 155707.58
D70: Non- Controlling Interest | F70: ₹ in MM | H70: ='BALANCE SHEET'!C40 -> 1326.1 | I70: ='BALANCE SHEET'!D40 -> 1483 | J70: ='BALANCE SHEET'!E40 -> 1812.8 | K70: ='BALANCE SHEET'!F40 -> 2094.3 | L70: ='BALANCE SHEET'!G40 -> 3897.1 | M70: =L70 -> 3897.1 | N70: =M70 -> 3897.1 | O70: =N70 -> 3897.1 | P70: =O70 -> 3897.1 | Q70: =P70 -> 3897.1
D71: Total Liabilities & Shareholder Equity | F71: ₹ in MM | H71: =SUM(H65,H69,H70) -> 82081.9 | I71: =SUM(I65,I69,I70) -> 99433.3 | J71: =SUM(J65,J69,J70) -> 115192.6 | K71: =SUM(K65,K69,K70) -> 140691.9 | L71: =SUM(L65,L69,L70) -> 137566.5 | M71: =SUM(M65,M69,M70) -> 151767.25 | N71: =SUM(N65,N69,N70) -> 164920.81 | O71: =SUM(O65,O69,O70) -> 178714.23 | ... Q71: =SUM(Q65,Q69,Q70) -> 207971.06
D73: Check | H73: =H71-H56 -> 0 | I73: =I71-I56 -> 0 | J73: =J71-J56 -> 0 | K73: =K71-K56 -> 0 | L73: =L71-L56 -> 0.2 | M73: =M71-M56 -> 0.2 | N73: =N71-N56 -> 0.2 | O73: =O71-O56 -> 0.2 | ... Q73: =Q71-Q56 -> 0.2
A77: Cash Flow Statement
C79: Operating Cash Flow
D80: Net Earings | F80: ₹ in MM | H80: ='Cash Flow Statement'!C5+'Cash Flow Statement'!C32 -> 7035.5 | I80: ='Cash Flow Statement'!D5+'Cash Flow Statement'!D32 -> 9764.1 | J80: ='Cash Flow Statement'!E5+'Cash Flow Statement'!E32 -> 14414.2 | K80: ='Cash Flow Statement'!F5+'Cash Flow Statement'!F32 -> 14473.8 | L80: ='Cash Flow Statement'!G5+'Cash Flow Statement'!G32 -> 10313.8 | M80: =M38 -> 17326.476 | N80: =N38 -> 18499.3 | O80: =O38 -> 19572.244 | P80: =P38 -> 20545.287 | Q80: =Q38 -> 21421.422
D81: Plus: Depreciation & Amortization | F81: ₹ in MM | H81: ='Cash Flow Statement'!C7 -> 1931.8 | I81: ='Cash Flow Statement'!D7 -> 2527.6 | J81: ='Cash Flow Statement'!E7 -> 2745.8 | K81: ='Cash Flow Statement'!F7 -> 3039.6 | L81: ='Cash Flow Statement'!G7 -> 3104.2 | M81: =-M32 -> 2654.5802 | N81: =-N32 -> 2531.7894 | O81: =-O32 -> 2394.8341 | P81: =-P32 -> 2249.9152 | Q81: =-Q32 -> 2101.7565
D82: Plus/Less : Adjustment for non-operating item | F82: ₹ in MM | H82: ='Cash Flow Statement'!C22-'Cash Flow Statement'!C7 -> 231.9 | I82: ='Cash Flow Statement'!D22-'Cash Flow Statement'!D7 -> 31.1 | J82: ='Cash Flow Statement'!E22-'Cash Flow Statement'!E7 -> -1099.4 | K82: ='Cash Flow Statement'!F22-'Cash Flow Statement'!F7 -> -953.6 | L82: ='Cash Flow Statement'!G22-'Cash Flow Statement'!G7 -> 139.3 | M82: =-M34-M35 -> -1214.6128 | N82: =-N34-N35 -> -1311.8054 | O82: =-O34-O35 -> -1398.8006 | P82: =-P34-P35 -> -1476.0801 | Q82: =-Q34-Q35 -> -1544.2847
D83: Plus/Less : Adjustment for operating Asset & liabities | F83: ₹ in MM | H83: =H115 -> -1402.7 | I83: =I115 -> -6472 | J83: =J115 -> -3411.6 | K83: =K115 -> -5449.6 | L83: =L115 -> 3267.7 | M83: =M115 -> -1833.1944 | N83: =N115 -> -1993.0972 | O83: =O115 -> -1783.9828 | ... Q83: =Q115 -> -1398.6498
D84: Cash From Operation | F84: ₹ in MM | H84: =SUM(H80:H83) -> 7796.5 | I84: =SUM(I80:I83) -> 5850.8 | J84: =SUM(J80:J83) -> 12649 | K84: =SUM(K80:K83) -> 11110.2 | L84: =SUM(L80:L83) -> 16825 | M84: =SUM(M80:M83) -> 16933.249 | N84: =SUM(N80:N83) -> 17726.187 | O84: =SUM(O80:O83) -> 18784.295 | ... Q84: =SUM(Q80:Q83) -> 20580.244
C86: Investing Cash Flow | F86: ₹ in MM
D87: Investment in Property & Equipnment | F87: ₹ in MM | H87: ='Cash Flow Statement'!C35 -> -5291.6 | I87: ='Cash Flow Statement'!D35 -> -3630.9 | J87: ='Cash Flow Statement'!E35 -> -1949.1 | K87: ='Cash Flow Statement'!F35 -> -3388.8 | L87: ='Cash Flow Statement'!G35 -> -2329.1 | M87: =-M119 -> -1455.2032 | N87: =-N119 -> -1194.0583 | O87: =-O119 -> -979.31806 | P87: =-P119 -> -802.75324 | Q87: =-Q119 -> -657.68786
D88: Sale of Property, Plant and Equipnment | F88: ₹ in MM | H88: ='Cash Flow Statement'!C36 -> 22.3 | I88: ='Cash Flow Statement'!D36 -> 154.5 | J88: ='Cash Flow Statement'!E36 -> 104.6 | K88: ='Cash Flow Statement'!F36 -> 109 | L88: ='Cash Flow Statement'!G36 -> 32 | M88: 0 | N88: 0 | O88: 0 | P88: 0 | Q88: 0
D89: Net Proceed from sale of Investment | F89: ₹ in MM | H89: ='Cash Flow Statement'!C37++'Cash Flow Statement'!C38+'Cash Flow Statement'!C39 -> 1662.2 | I89: ='Cash Flow Statement'!D37++'Cash Flow Statement'!D38+'Cash Flow Statement'!D39 -> -4453.9 | J89: ='Cash Flow Statement'!E37++'Cash Flow Statement'!E38+'Cash Flow Statement'!E39 -> -8935.2 | K89: ='Cash Flow Statement'!F37++'Cash Flow Statement'!F38+'Cash Flow Statement'!F39 -> -12051.1 | L89: ='Cash Flow Statement'!G37++'Cash Flow Statement'!G38+'Cash Flow Statement'!G39 -> 1954.5 | M89: =L54-M54 -> 0 | N89: =M54-N54 -> 0 | O89: =N54-O54 -> 0 | P89: =O54-P54 -> 0 | Q89: =P54-Q54 -> 0
D90: Dividend received | F90: ₹ in MM | H90: ='Cash Flow Statement'!C40 -> 1.2 | I90: ='Cash Flow Statement'!D40 -> 1.1 | J90: ='Cash Flow Statement'!E40 -> 0.2 | K90: ='Cash Flow Statement'!F40 -> 1.9 | L90: ='Cash Flow Statement'!G40 -> 1.9
D91: Interest received | F91: ₹ in MM | H91: ='Cash Flow Statement'!C41 -> 436.7 | I91: ='Cash Flow Statement'!D41 -> 509.2 | J91: ='Cash Flow Statement'!E41 -> 785.7 | K91: ='Cash Flow Statement'!F41 -> 977.7 | L91: ='Cash Flow Statement'!G41 -> 1469.1 | M91: =M35 -> 1832.5738 | N91: =N35 -> 1929.7664 | O91: =O35 -> 2016.7616 | P91: =P35 -> 2094.0411 | Q91: =Q35 -> 2162.2457
D92: Rent received | F92: ₹ in MM | H92: ='Cash Flow Statement'!C42 -> 5.3 | I92: ='Cash Flow Statement'!D42 -> 6.5 | J92: ='Cash Flow Statement'!E42 -> 8.4 | K92: ='Cash Flow Statement'!F42 -> 0 | L92: ='Cash Flow Statement'!G42 -> 0
D93: Cash From Investing | F93: ₹ in MM | H93: =SUM(H87:H92) -> -3163.9 | I93: =SUM(I87:I92) -> -7413.5 | J93: =SUM(J87:J92) -> -9985.4 | K93: =SUM(K87:K92) -> -14351.3 | L93: =SUM(L87:L92) -> 1128.4 | M93: =SUM(M87:M92) -> 377.37063 | N93: =SUM(N87:N92) -> 735.70815 | O93: =SUM(O87:O92) -> 1037.4436 | ... Q93: =SUM(Q87:Q92) -> 1504.5579
C95: Financing cash Flow
D96: Issuance(Repayment) of Debt | F96: ₹ in MM | H96: ='Cash Flow Statement'!C45+'Cash Flow Statement'!C46+'Cash Flow Statement'!C49 -> -1057.3 | I96: ='Cash Flow Statement'!D45+'Cash Flow Statement'!D46+'Cash Flow Statement'!D49 -> 5837.7 | J96: ='Cash Flow Statement'!E45+'Cash Flow Statement'!E46+'Cash Flow Statement'!E49 -> 1166.5 | K96: ='Cash Flow Statement'!F45+'Cash Flow Statement'!F46+'Cash Flow Statement'!F49 -> 8416.1 | L96: ='Cash Flow Statement'!G45+'Cash Flow Statement'!G46+'Cash Flow Statement'!G49 -> -13023.2 | M96: =M125 -> 0 | N96: =N125 -> 0 | O96: =O125 -> 0 | P96: =P125 -> 0 | Q96: =Q125 -> 0
D97: Issuance(Repayment) of Preferrance Share - NCI | F97: ₹ in MM | H97: ='Cash Flow Statement'!C47 -> 0 | I97: ='Cash Flow Statement'!D47 -> 0 | J97: ='Cash Flow Statement'!E47 -> 0 | K97: ='Cash Flow Statement'!F47 -> 0 | L97: ='Cash Flow Statement'!G47 -> 1614.8 | M97: 0 | N97: 0 | O97: 0 | P97: 0 | Q97: 0
D98: Dividend Paid | F98: ₹ in MM | H98: ='Cash Flow Statement'!C48 -> -2185.8 | I98: ='Cash Flow Statement'!D48 -> -4395.6 | J98: ='Cash Flow Statement'!E48 -> -3347.8 | K98: ='Cash Flow Statement'!F48 -> -4219.1 | L98: ='Cash Flow Statement'!G48 -> -5295.2 | M98: =-M38*M16 -> -5714.1217 | N98: =-N38*N16 -> -6100.9088 | O98: =-O38*O16 -> -6454.7566 | P98: =-P38*P16 -> -6775.6578 | Q98: =-Q38*Q16 -> -7064.5994
D99: Interest Paid | F99: ₹ in MM | H99: ='Cash Flow Statement'!C50 -> -546.3 | I99: ='Cash Flow Statement'!D50 -> -650.6 | J99: ='Cash Flow Statement'!E50 -> -536.2 | K99: ='Cash Flow Statement'!F50 -> -401.3 | L99: ='Cash Flow Statement'!G50 -> -904.6 | M99: =M127 -> -617.96105 | N99: =N127 -> -617.96105 | O99: =O127 -> -617.96105 | P99: =P127 -> -617.96105 | Q99: =Q127 -> -617.96105
D100: Cash From Financing | F100: ₹ in MM | H100: =SUM(H96:H99) -> -3789.4 | I100: =SUM(I96:I99) -> 791.5 | J100: =SUM(J96:J99) -> -2717.5 | K100: =SUM(K96:K99) -> 3795.7 | L100: =SUM(L96:L99) -> -17608.2 | M100: =SUM(M96:M99) -> -6332.0828 | N100: =SUM(N96:N99) -> -6718.8699 | O100: =SUM(O96:O99) -> -7072.7177 | ... Q100: =SUM(Q96:Q99) -> -7682.5604
D102: Net Increase (Decrease) in Cash | F102: ₹ in MM | H102: =SUM(H84,H93,H100) -> 843.2 | I102: =SUM(I84,I93,I100) -> -771.2 | J102: =SUM(J84,J93,J100) -> -53.9 | K102: =SUM(K84,K93,K100) -> 554.6 | L102: =SUM(L84,L93,L100) -> 345.2 | M102: =SUM(M84,M93,M100) -> 10978.537 | N102: =SUM(N84,N93,N100) -> 11743.025 | O102: =SUM(O84,O93,O100) -> 12749.021 | ... Q102: =SUM(Q84,Q93,Q100) -> 14402.241
D103: Opening Cash Balance | F103: ₹ in MM | H103: =SUM('Cash Flow Statement'!C53:C54) -> 1647.3 | I103: =SUM('Cash Flow Statement'!D53:D54) -> 2530.6 | J103: =SUM('Cash Flow Statement'!E53:E54) -> 1796.1 | K103: =SUM('Cash Flow Statement'!F53:F54) -> 1767.2 | L103: =SUM('Cash Flow Statement'!G53:G54) -> 2392.8 | M103: =L104 -> 2738 | N103: =M104 -> 13716.537 | O103: =N104 -> 25459.562 | P103: =O104 -> 38208.583 | Q103: =P104 -> 51840.629
D104: Closing Balance | F104: ₹ in MM | H104: =SUM(H102:H103) -> 2490.5 | I104: =SUM(I102:I103) -> 1759.4 | J104: =SUM(J102:J103) -> 1742.2 | K104: =SUM(K102:K103) -> 2321.8 | L104: =SUM(L102:L103) -> 2738 | M104: =SUM(M102:M103) -> 13716.537 | N104: =SUM(N102:N103) -> 25459.562 | O104: =SUM(O102:O103) -> 38208.583 | ... Q104: =SUM(Q102:Q103) -> 66242.87
A108: Supporting Schedule
C110: Working Capital
D111: Account Recievable | F111: ₹ in MM | H111: ='Cash Flow Statement'!C25 -> -1558.5 | I111: ='Cash Flow Statement'!D25 -> -2574.4 | J111: ='Cash Flow Statement'!E25 -> -257.6 | K111: ='Cash Flow Statement'!F25 -> -2217.5 | L111: ='Cash Flow Statement'!G25 -> -1347.1 | M111: =L47-M47 -> -1098.3401 | N111: =M47-N47 -> -1189.0773 | O111: =N47-O47 -> -1064.3201 | P111: =O47-P47 -> -945.45538 | Q111: =P47-Q47 -> -834.43132
D112: Inventory | F112: ₹ in MM | H112: ='Cash Flow Statement'!C27 -> -373 | I112: ='Cash Flow Statement'!D27 -> -2817.4 | J112: ='Cash Flow Statement'!E27 -> -4977 | K112: ='Cash Flow Statement'!F27 -> -6731.4 | L112: ='Cash Flow Statement'!G27 -> 4734.1 | M112: =L48-M48 -> -3323.2524 | N112: =M48-N48 -> -1559.1852 | O112: =N48-O48 -> -1395.5966 | P112: =O48-P48 -> -1239.7344 | Q112: =P48-Q48 -> -1094.1534
D113: Account Payable | F113: ₹ in MM | H113: ='Cash Flow Statement'!C28 -> -109.5 | I113: ='Cash Flow Statement'!D28 -> -37.4 | J113: ='Cash Flow Statement'!E28 -> 2124.2 | K113: ='Cash Flow Statement'!F28 -> 3344.9 | L113: ='Cash Flow Statement'!G28 -> 145.1 | M113: =M60-L60 -> 2588.3982 | N113: =N60-M60 -> 755.16534 | O113: =O60-N60 -> 675.93393 | P113: =P60-O60 -> 600.44468 | Q113: =Q60-P60 -> 529.93495
D114: Others | F114: ₹ in MM | H114: ='Cash Flow Statement'!C29+'Cash Flow Statement'!C26 -> 638.3 | I114: ='Cash Flow Statement'!D29+'Cash Flow Statement'!D26 -> -1042.8 | J114: ='Cash Flow Statement'!E29+'Cash Flow Statement'!E26 -> -301.2 | K114: ='Cash Flow Statement'!F29+'Cash Flow Statement'!F26 -> 154.4 | L114: ='Cash Flow Statement'!G29+'Cash Flow Statement'!G26 -> -264.4 | M114: =L49-M49+M61-L61 -> 0 | N114: =M49-N49+N61-M61 -> 0 | O114: =N49-O49+O61-N61 -> 0 | P114: =O49-P49+P61-O61 -> 0 | Q114: =P49-Q49+Q61-P61 -> 0
D115: Total | F115: ₹ in MM | H115: =SUM(H111:H114) -> -1402.7 | I115: =SUM(I111:I114) -> -6472 | J115: =SUM(J111:J114) -> -3411.6 | K115: =SUM(K111:K114) -> -5449.6 | L115: =SUM(L111:L114) -> 3267.7 | M115: =SUM(M111:M114) -> -1833.1944 | N115: =SUM(N111:N114) -> -1993.0972 | O115: =SUM(O111:O114) -> -1783.9828 | ... Q115: =SUM(Q111:Q114) -> -1398.6498
C117: Depreciation
D118: PPE Opening | F118: ₹ in MM | I118: =H121 -> 26428.4 | J118: =I121 -> 28725.3 | K118: =J121 -> 27908.7 | L118: =K121 -> 28381.2 | M118: =L121 -> 25929 | N118: =M121 -> 24729.623 | O118: =N121 -> 23391.892 | P118: =O121 -> 21976.376 | Q118: =P121 -> 20529.214
D119: Plus Capex | F119: ₹ in MM | I119: =I121-I120-I118 -> 4824.5 | J119: =J121-J120-J118 -> 1929.2 | K119: =K121-K120-K118 -> 3512.1 | L119: =L121-L120-L118 -> 652 | M119: =(M25-L25)/M20 -> 1455.2032 | N119: =(N25-M25)/N20 -> 1194.0583 | O119: =(O25-N25)/O20 -> 979.31806 | P119: =(P25-O25)/P20 -> 802.75324 | Q119: =(Q25-P25)/Q20 -> 657.68786
D120: Less Depreciation | F120: ₹ in MM | H120: =-H81 -> -1931.8 | I120: =-I81 -> -2527.6 | J120: =-J81 -> -2745.8 | K120: =-K81 -> -3039.6 | L120: =-L81 -> -3104.2 | M120: =-M118*M12 -> -2654.5802 | N120: =-N118*N12 -> -2531.7894 | O120: =-O118*O12 -> -2394.8341 | P120: =-P118*P12 -> -2249.9152 | Q120: =-Q118*Q12 -> -2101.7565
D121: PPE Closing | F121: ₹ in MM | H121: =H52 -> 26428.4 | I121: =I52 -> 28725.3 | J121: =J52 -> 27908.7 | K121: =K52 -> 28381.2 | L121: =L52 -> 25929 | M121: =SUM(M118:M120) -> 24729.623 | N121: =SUM(N118:N120) -> 23391.892 | O121: =SUM(O118:O120) -> 21976.376 | P121: =SUM(P118:P120) -> 20529.214 | Q121: =SUM(Q118:Q120) -> 19085.145
C123: Debt & Interest Schedule
...

Sheet Scenario
A1: Alkem Laboratories LTD
A2: Scenarios
C4: Scenarios | E4: Growth (%) | H4: =Model!M2 -> 2024 | I4: =Model!N2 -> 2025 | J4: =Model!O2 -> 2026 | K4: =Model!P2 -> 2027 | L4: =Model!Q2 -> 2028
D5: Base Case | E5: =AVERAGE(Model!I8:L8) -> 0.12172338 | H5: =E5 -> 0.12172338 | I5: =H5*(1-$E$8) -> 0.10346487 | J5: =I5*(1-$E$8) -> 0.087945141 | K5: =J5*(1-$E$8) -> 0.07475337 | L5: =K5*(1-$E$8) -> 0.063540364 | M5: 0.06
D6: Bull Case | E6: =MAX(Model!H8:L8) -> 0.19956887 | H6: =E6 -> 0.19956887 | I6: =H6*(1-$E$8) -> 0.16963354 | J6: =I6*(1-$E$8) -> 0.14418851 | K6: =J6*(1-$E$8) -> 0.12256023 | L6: =K6*(1-$E$8) -> 0.1041762
D7: Bear Case | E7: =MIN(Model!I8:L8) -> 0.062395438 | H7: =E7 -> 0.062395438 | I7: =H7*(1-$E$8) -> 0.053036123 | J7: =I7*(1-$E$8) -> 0.045080704 | K7: =J7*(1-$E$8) -> 0.038318599 | L7: =K7*(1-$E$8) -> 0.032570809
D8: Annual Growth Tampering | E8: =0.15 -> 0.15

Sheet Market
A1: Alkem Laboratories LTD
A2: Equity Market Return
A4: Index Name | B4: Date | C4: Total Returns Index | F4: Index | G4: NIFTY 50
A5: NIFTY 50 | B5: 45323 | C5: 31898.06
A6: NIFTY 50 | B6: 45322 | C6: 31939.59 | F6: Year Frac | G6: =YEARFRAC(B2476,B5) -> 9.9944444
A7: NIFTY 50 | B7: 45321 | C7: 31640.24
A8: NIFTY 50 | B8: 45320 | C8: 31957.05 | F8: Market Return | G8: =_xlfn.RRI(G6,C2476,C5) -> 0.15109568
A9: NIFTY 50 | B9: 45316 | C9: 31391.07
A10: NIFTY 50 | B10: 45315 | C10: 31540.07
A11: NIFTY 50 | B11: 45314 | C11: 31223.3
A12: NIFTY 50 | B12: 45311 | C12: 31712.86
A13: NIFTY 50 | B13: 45310 | C13: 31787.24
A14: NIFTY 50 | B14: 45309 | C14: 31538.4
A15: NIFTY 50 | B15: 45308 | C15: 31699.64
A16: NIFTY 50 | B16: 45307 | C16: 32376.1
A17: NIFTY 50 | B17: 45306 | C17: 32471.8
A18: NIFTY 50 | B18: 45303 | C18: 32173.66
A19: NIFTY 50 | B19: 45302 | C19: 31810.18
A20: NIFTY 50 | B20: 45301 | C20: 31768.3
... A2476: NIFTY 50 | B2476: 41673 | C2476: 7816.09

Sheet Comp Valuation
A1: Alkem Laboratories LTD
E4: Market Data | M4: Financial Data | Q4: Valuation
E5: Ticker | F5: Price | G5: Shares | H5: Market Cap | I5: Debt | J5: Cash | K5: EV | M5: Sales | N5: EBITDA | O5: Earning | Q5: Ev/Sale | R5: Ev/EBITDA | S5: P/E
D6: Company | F6: (₹/Share) | G6: M | H6: ₹ MM | K6: ₹ MM | M6: ₹ MM | N6: ₹ MM | O6: ₹ MM | Q6: x | R6: x | S6: x
D8: Dr. Reddy's Laboratories Limited | E8: 500124 | F8: 6445 | G8: 166.62 | H8: =F8*G8 -> 1073865.9 | I8: 19766.03 | J8: 72239.47 | K8: =H8+I8-J8 -> 1021392.5 | M8: 270140.78 | N8: 80632.4 | O8: 51982.55 | Q8: =K8/M8 -> 3.7809636 | R8: =K8/N8 -> 12.667271 | S8: =H8/O8 -> 20.6582
D9: Zydus Lifesciences Limited | E9: ZYDUSLIFE | F9: 923.25 | G9: 1012.08 | H9: =F9*G9 -> 934402.86 | I9: 1910.79 | J9: 15129.96 | K9: =H9+I9-J9 -> 921183.69 | M9: 187864.45 | N9: 49048.66 | O9: 29610.72 | Q9: =K9/M9 -> 4.9034487 | R9: =K9/N9 -> 18.781016 | S9: =H9/O9 -> 31.556236
D10: Torrent Pharmaceuticals Limited | E10: 500420 | F10: 2627.1 | G10: 338.34 | H10: =F10*G10 -> 888853.01 | I10: 44697.86 | J10: 7866 | K10: =H10+I10-J10 -> 925684.87 | M10: 104303.15 | N10: 31025.41 | O10: 14878.34 | Q10: =K10/M10 -> 8.8749465 | R10: =K10/N10 -> 29.836346 | S10: =H10/O10 -> 59.74141
D11: Mankind Pharma Limited | E11: MANKIND | F11: 2154.05 | G11: 400.95 | H11: =F11*G11 -> 863666.35 | I11: 1786.67 | J11: 23159 | K11: =H11+I11-J11 -> 842294.02 | M11: 99037.7 | N11: 23053.59 | O11: 17197.05 | Q11: =K11/M11 -> 8.5047817 | R11: =K11/N11 -> 36.536349 | S11: =H11/O11 -> 50.221773
D12: Lupin Limited | E12: 500257 | F12: 1612.2 | G12: 457.21 | H12: =F12*G12 -> 737113.96 | I12: 37684.11 | J12: 17254 | K12: =H12+I12-J12 -> 757544.07 | M12: 193799.04 | N12: 31333.96 | O12: 17833.44 | Q12: =K12/M12 -> 3.9089155 | R12: =K12/N12 -> 24.176455 | S12: =H12/O12 -> 41.333246
D13: Aurobindo Pharma Limited | E13: AUROPHARMA | F13: 1043.8 | G13: 586.5 | H13: =F13*G13 -> 612188.7 | I13: 66201.73 | J13: 71184 | K13: =H13+I13-J13 -> 607206.43 | M13: 277103.85 | N13: 48727.42 | O13: 27586.32 | Q13: =K13/M13 -> 2.1912595 | R13: =K13/N13 -> 12.461288 | S13: =H13/O13 -> 22.191749
D14: Abbott India Limited | E14: 500488 | F14: 28686.2 | G14: 21.25 | H14: =F14*G14 -> 609581.75 | I14: 911.48 | J14: 19432 | K14: =H14+I14-J14 -> 591061.23 | M14: 57287.35 | N14: 13599.67 | O14: 11406.77 | Q14: =K14/M14 -> 10.317482 | R14: =K14/N14 -> 43.461439 | S14: =H14/O14 -> 53.440347
D15: GlaxoSmithKline Pharmaceuticals Limited | E15: 500660 | F15: 2169 | G15: 169.37 | H15: =F15*G15 -> 367363.53 | I15: 212.88 | J15: 15984 | K15: =H15+I15-J15 -> 351592.41 | M15: 32971.9 | N15: 7958.68 | O15: 5266.43 | Q15: =K15/M15 -> 10.663395 | R15: =K15/N15 -> 44.177227 | S15: =H15/O15 -> 69.755704
D16: Ipca Laboratories Limited | E16: IPCALAB | F16: 1217.7 | G16: 253.64 | H16: =F16*G16 -> 308857.43 | I16: 19789.53 | J16: 9300 | K16: =H16+I16-J16 -> 319346.96 | M16: 71529.13 | N16: 11088.19 | O16: 5618.65 | Q16: =K16/M16 -> 4.4645721 | R16: =K16/N16 -> 28.800639 | S16: =H16/O16 -> 54.970042
D17: Gland Pharma Limited | E17: GLAND | F17: 1861.1 | G17: 164.72 | H17: =F17*G17 -> 306560.39 | I17: 3555.02 | J17: 21355 | K17: =H17+I17-J17 -> 288760.41 | M17: 48912.58 | N17: 10292.17 | O17: 6559.04 | Q17: =K17/M17 -> 5.9036021 | R17: =K17/N17 -> 28.05632 | S17: =H17/O17 -> 46.738607
D19: Average | Q19: =AVERAGE(Q8:Q17) -> 6.3513368 | R19: =AVERAGE(R8:R17) -> 27.895435 | S19: =AVERAGE(S8:S17) -> 45.060731
D20: Median | Q20: =MEDIAN(Q8:Q17) -> 5.4035254 | R20: =MEDIAN(R8:R17) -> 28.428479 | S20: =MEDIAN(S8:S17) -> 48.48019
D22: Alkem Laboratories Limited | E22: ALKEM | F22: 5421.15 | G22: 119.57 | H22: =F22*G22 -> 648206.91 | I22: 14367.84 | J22: 35943.4 | K22: =H22+I22-J22 -> 626631.35 | M22: 125802.83 | N22: 21840.24 | O22: 15664.56 | Q22: =K22/M22 -> 4.9810592 | R22: =K22/N22 -> 28.691596 | S22: =H22/O22 -> 41.380473
D24: Metric | E24: Comp | F24: EV | G24: Net Debt | H24: Equity Value | I24: Share | J24: Share Price
D25: EV/Revenue | E25: =Q19 -> 6.3513368 | F25: =E25*M22 -> 799016.14 | G25: =J22-I22 -> 21575.56 | H25: =F25-G25 -> 777440.58 | I25: =$G$22 -> 119.57 | J25: =H25/I25 -> 6501.9702
D26: Ev/EBITDA | E26: =R19 -> 27.895435 | F26: =E26*N22 -> 609243 | G26: =G25 -> 21575.56 | H26: =F26-G26 -> 587667.44 | I26: =$G$22 -> 119.57 | J26: =H26/I26 -> 4914.8402
D27: P/E | E27: =S19 -> 45.060731 | F27: =H27+G27 -> 727432.09 | G27: =G26 -> 21575.56 | H27: =E27*O22 -> 705856.53 | I27: =$G$22 -> 119.57 | J27: =H27/I27 -> 5903.2912

Sheet WACC
A1: Alkem Laboratories LTD
A2: Weighted-Average Cost of Capital (WACC)
A4: Comparable Companies Beta
D7: Company | E7: Ticker | H7: Equity Value | I7: Total Debt | J7: Debt/Equity | K7: Debt/Capital | L7: Tax Rate | M7: Levered Beta | N7: Unlevered Beta
D9: Dr. Reddy's Laboratories Limited | E9: 500124 | H9: ='Comp Valuation'!H8 -> 1073865.9 | I9: ='Comp Valuation'!I8 -> 19766.03 | J9: =I9/H9 -> 0.018406423 | K9: =I9/(H9+I9) -> 0.01807375 | L9: 0.2446 | M9: 0.35 | N9: =M9/(1+J9*(1-L9)) -> 0.34520026
D10: Zydus Lifesciences Limited | E10: ZYDUSLIFE | H10: ='Comp Valuation'!H9 -> 934402.86 | I10: ='Comp Valuation'!I9 -> 1910.79 | J10: =I10/H10 -> 0.0020449317 | K10: =I10/(H10+I10) -> 0.0020407585 | L10: 0.2055 | M10: 0.49 | N10: =M10/(1+J10*(1-L10)) -> 0.48920519
D11: Torrent Pharmaceuticals Limited | E11: 500420 | H11: ='Comp Valuation'!H10 -> 888853.01 | I11: ='Comp Valuation'!I10 -> 44697.86 | J11: =I11/H11 -> 0.050287122 | K11: =I11/(H11+I11) -> 0.047879405 | L11: 0.3064 | M11: 0.28 | N11: =M11/(1+J11*(1-L11)) -> 0.27056299
D12: Mankind Pharma Limited | E12: MANKIND | H12: ='Comp Valuation'!H11 -> 863666.35 | I12: ='Comp Valuation'!I11 -> 1786.67 | J12: =I12/H12 -> 0.002068704 | K12: =I12/(H12+I12) -> 0.0020644333 | L12: 0.2023
D13: Lupin Limited | E13: 500257 | H13: ='Comp Valuation'!H12 -> 737113.96 | I13: ='Comp Valuation'!I12 -> 37684.11 | J13: =I13/H13 -> 0.051123859 | K13: =I13/(H13+I13) -> 0.048637331 | L13: 0.171 | M13: 0.66 | N13: =M13/(1+J13*(1-L13)) -> 0.63316539
D14: Aurobindo Pharma Limited | E14: AUROPHARMA | H14: ='Comp Valuation'!H13 -> 612188.7 | I14: ='Comp Valuation'!I13 -> 66201.73 | J14: =I14/H14 -> 0.10813942 | K14: =I14/(H14+I14) -> 0.097586474 | L14: 0.2867 | M14: 0.62 | N14: =M14/(1+J14*(1-L14)) -> 0.57560056
D15: Abbott India Limited | E15: 500488 | H15: ='Comp Valuation'!H14 -> 609581.75 | I15: ='Comp Valuation'!I14 -> 911.48 | J15: =I15/H15 -> 0.0014952547 | K15: =I15/(H15+I15) -> 0.0014930223 | L15: 0.2544 | M15: 0.05 | N15: =M15/(1+J15*(1-L15)) -> 0.049944319
D16: GlaxoSmithKline Pharmaceuticals Limited | E16: 500660 | H16: ='Comp Valuation'!H15 -> 367363.53 | I16: ='Comp Valuation'!I15 -> 212.88 | J16: =I16/H16 -> 0.00057948049 | K16: =I16/(H16+I16) -> 0.00057914489 | L16: 0.2809 | M16: 0.25 | N16: =M16/(1+J16*(1-L16)) -> 0.24989587
D17: Ipca Laboratories Limited | E17: IPCALAB | H17: ='Comp Valuation'!H16 -> 308857.43 | I17: ='Comp Valuation'!I16 -> 19789.53 | J17: =I17/H17 -> 0.06407335 | K17: =I17/(H17+I17) -> 0.060215163 | L17: 0.3245 | M17: 0.22 | N17: =M17/(1+J17*(1-L17)) -> 0.21087309
D18: Gland Pharma Limited | E18: GLAND | H18: ='Comp Valuation'!H17 -> 306560.39 | I18: ='Comp Valuation'!I17 -> 3555.02 | J18: =I18/H18 -> 0.011596475 | K18: =I18/(H18+I18) -> 0.011463539 | L18: 0.3033 | M18: 0.42 | N18: =M18/(1+J18*(1-L18)) -> 0.4166339
D20: Average | J20: =AVERAGE(J9:J18) -> 0.030981502 | K20: =AVERAGE(K9:K18) -> 0.029003302 | L20: =AVERAGE(L9:L18) -> 0.25796 | M20: =AVERAGE(M9:M18) -> 0.37111111 | N20: =AVERAGE(N9:N18) -> 0.36012017
D21: Median | J21: =MEDIAN(J9:J18) -> 0.015001449 | K21: =MEDIAN(K9:K18) -> 0.014768644 | L21: =MEDIAN(L9:L18) -> 0.26765 | M21: =MEDIAN(M9:M18) -> 0.35 | N21: =MEDIAN(N9:N18) -> 0.34520026
D23: Alkem Laboratories Limited | E23: ALKEM | H23: ='Comp Valuation'!H22 -> 648206.91 | I23: ='Comp Valuation'!I22 -> 14367.84 | J23: =I23/H23 -> 0.022165515 | K23: =I23/(H23+I23) -> 0.021684859 | L23: 0.1568
D25: WACC Calculation
D27: Total Capital Structure
D29: Proportion of debt | E29: =J20 -> 0.030981502
D30: Proportion of Equity | E30: =1-E29 -> 0.9690185
D31: Current Capital Structure
D32: Market Cap | E32: =H23 -> 648206.91
D33: Total Debt | E33: =I23 -> 14367.84
D34: Debt/Equity | E34: =I23/H23 -> 0.022165515
D36: Cost Of Debt
D37: Pre-tax Cost of Debt | E37: =Model!M13 -> 0.044244999
D38: Tax Rate | E38: =L23 -> 0.1568
D39: After-Tax Cost of Debt | E39: =E37*(1-E38) -> 0.037307383
D41: Cost Of Equity
D42: Risk Free Rate | E42: 0.071
D43: Equity Market Return | E43: 0.151
D44: Equity Risk Premium | E44: =E43-E42 -> 0.08
D45: Levered Equity Beta | E45: =N21*(1+E34*(1-E38)) -> 0.35165204
D46: Cost of Equity | E46: =E42+(E44*E45) -> 0.099132163
D48: WACC | E48: =E29*E39+E46*E30 -> 0.097216739

Sheet Beta
A1: Alkem Laboratories LTD
A2: Company Beta
A4: Month | B4: Index Close price | C4: % Change Monthly | D4: Stock Close Price | E4: % Change Monthly
A6: 43497 | B6: 35867.44 | D6: 1746.6 | G6: Max | H6: =MAX(D42:D66) -> 5192.6
A7: 43525 | B7: 38672.91 | C7: =B7/B6-1 -> 0.078217737 | D7: 1751.8 | E7: =D7/D6-1 -> 0.0029772129 | G7: Min | H7: =MIN(D42:D66) -> 2975.5
A8: 43556 | B8: 39031.55 | C8: =B8/B7-1 -> 0.009273675 | D8: 1719.95 | E8: =D8/D7-1 -> -0.018181299
A9: 43586 | B9: 39714.2 | C9: =B9/B8-1 -> 0.017489697 | D9: 1790.05 | E9: =D9/D8-1 -> 0.040756999 | G9: Beta | H9: =SLOPE(E7:E66,C7:C66) -> 0.57707095
A10: 43617 | B10: 39394.64 | C10: =B10/B9-1 -> -0.0080464922 | D10: 1668.65 | E10: =D10/D9-1 -> -0.067819335
A11: 43647 | B11: 37481.12 | C11: =B11/B10-1 -> -0.048573105 | D11: 1736.85 | E11: =D11/D10-1 -> 0.040871363
A12: 43678 | B12: 37332.79 | C12: =B12/B11-1 -> -0.0039574591 | D12: 1816.85 | E12: =D12/D11-1 -> 0.046060397
A13: 43709 | B13: 38667.33 | C13: =B13/B12-1 -> 0.035747127 | D13: 1903.85 | E13: =D13/D12-1 -> 0.047885076
A14: 43739 | B14: 40129.05 | C14: =B14/B13-1 -> 0.037802455 | D14: 1989.85 | E14: =D14/D13-1 -> 0.045171626
A15: 43770 | B15: 40793.81 | C15: =B15/B14-1 -> 0.016565555 | D15: 2025.2 | E15: =D15/D14-1 -> 0.017765158
A16: 43800 | B16: 41253.74 | C16: =B16/B15-1 -> 0.011274505 | D16: 2013.55 | E16: =D16/D15-1 -> -0.0057525183
A17: 43831 | B17: 40723.49 | C17: =B17/B16-1 -> -0.01285338 | D17: 2394.3 | E17: =D17/D16-1 -> 0.18909389
A18: 43862 | B18: 38297.29 | C18: =B18/B17-1 -> -0.059577409 | D18: 2627.9 | E18: =D18/D17-1 -> 0.09756505
A19: 43891 | B19: 29468.49 | C19: =B19/B18-1 -> -0.23053328 | D19: 2328.85 | E19: =D19/D18-1 -> -0.11379809
A20: 43922 | B20: 33717.62 | C20: =B20/B19-1 -> 0.14419232 | D20: 2608.45 | E20: =D20/D19-1 -> 0.12005926
A21: 43952 | B21: 32424.1 | C21: =B21/B20-1 -> -0.038363325 | D21: 2261.2 | E21: =D21/D20-1 -> -0.13312504
... A66: 45323 | B66: 72790.13 | C66: =B66/B65-1 -> 0.014466752 | D66: 5060.3 | E66: =D66/D65-1 -> 0.013194778

Sheet Summary
A1: Alkem Laboratories LTD
A2: Valuation Summary - Football Field
A4: Football Field Data
K5: Market
H6: Comp | I6: DCF | J6: 52-week hi/Lo | K6: Consenses
D7: High | H7: =MAX('Comp Valuation'!J25:J27) -> 6501.9702 | I7: 5987.1571 | J7: =Beta!H6 -> 5192.6 | K7: 5500
D8: High | H8: =H7 -> 6501.9702 | I8: =I7 -> 5987.1571 | J8: =J7 -> 5192.6 | K8: =K7 -> 5500
D9: Low | H9: =MIN('Comp Valuation'!J25:J27) -> 4914.8402 | I9: 4351.9199 | J9: =Beta!H7 -> 2975.5 | K9: =4800 -> 4800
D10: Low | H10: =H9 -> 4914.8402 | I10: =I9 -> 4351.9199 | J10: =J9 -> 2975.5 | K10: =K9 -> 4800
A12: Valuation Summary Chart
R143: =(M147+M150)*E135 -> 0
R144: =M153*(1+E136)/(E137-E136) -> #DIV/0!
R145: =AVERAGE(R143:R144) -> #DIV/0!
